{
  "Direccion UMF 23": {
    "zona": "CARBONÍFERA",
    "vacunas": {
      "ANTIALACRAN": {
        "unidad": 5,
        "almacen": 252,
        "total": 257
      },
      "BCG": {
        "unidad": 12,
        "almacen": 176,
        "total": 188
      },
      "COVID-19": {
        "unidad": 2,
        "almacen": 95,
        "total": 97
      },
      "DOBLE VIRAL (SR)": {
        "unidad": 200,
        "almacen": 60,
        "total": 260
      },
      "DPT": {
        "unidad": 25,
        "almacen": 578,
        "total": 603
      },
      "HEPATITIS A": {
        "unidad": 20,
        "almacen": 8,
        "total": 28
      },
      "HEPATITIS A AD...": {
        "unidad": 43,
        "almacen": 64,
        "total": 107
      },
      "HEPATITIS B": {
        "unidad": 50,
        "almacen": 264,
        "total": 314
      },
      "HEXAVALENTE": {
        "unidad": 57,
        "almacen": 217,
        "total": 274
      },
      "INFLUENZA TET...": {
        "unidad": 30,
        "almacen": 0,
        "total": 30
      },
      "NEUMO 13 V": {
        "unidad": 10,
        "almacen": 0,
        "total": 10
      },
      "NEUMO 20 V": {
        "unidad": 400,
        "almacen": 1620,
        "total": 2020
      },
      "ROTAVIRUS": {
        "unidad": 16,
        "almacen": 0,
        "total": 16
      },
      "TDPA": {
        "unidad": 220,
        "almacen": 1144,
        "total": 1364
      },
      "TRIPLE VIRAL (S...)": {
        "unidad": 1300,
        "almacen": 13375,
        "total": 14675
      },
      "VACUNA ANTIR...": {
        "unidad": 3,
        "almacen": 2,
        "total": 5
      }
    }
  },
  "Direccion UMF 25": {
    "zona": "CARBONÍFERA",
    "vacunas": {
      "BCG": {
        "unidad": 0,
        "almacen": 176,
        "total": 176
      },
      "DOBLE VIRAL (SR)": {
        "unidad": 0,
        "almacen": 60,
        "total": 60
      },
      "DPT": {
        "unidad": 0,
        "almacen": 578,
        "total": 578
      },
      "HEPATITIS A AD...": {
        "unidad": 0,
        "almacen": 64,
        "total": 64
      },
      "HEPATITIS B": {
        "unidad": 0,
        "almacen": 264,
        "total": 264
      },
      "HEXAVALENTE": {
        "unidad": 0,
        "almacen": 217,
        "total": 217
      },
      "NEUMO 20 V": {
        "unidad": 0,
        "almacen": 1620,
        "total": 1620
      },
      "TDPA": {
        "unidad": 0,
        "almacen": 1144,
        "total": 1144
      },
      "TRIPLE VIRAL (S...)": {
        "unidad": 0,
        "almacen": 13375,
        "total": 13375
      }
    }
  },
  "Direccion UMF 26": {
    "zona": "CARBONÍFERA",
    "vacunas": {
      "BCG": {
        "unidad": 0,
        "almacen": 176,
        "total": 176
      },
      "DOBLE VIRAL (SR)": {
        "unidad": 0,
        "almacen": 60,
        "total": 60
      },
      "DPT": {
        "unidad": 0,
        "almacen": 578,
        "total": 578
      },
      "HEPATITIS A AD...": {
        "unidad": 0,
        "almacen": 64,
        "total": 64
      },
      "HEPATITIS B": {
        "unidad": 0,
        "almacen": 264,
        "total": 264
      },
      "HEXAVALENTE": {
        "unidad": 0,
        "almacen": 217,
        "total": 217
      },
      "NEUMO 20 V": {
        "unidad": 0,
        "almacen": 1620,
        "total": 1620
      },
      "TDPA": {
        "unidad": 5,
        "almacen": 1144,
        "total": 1149
      },
      "TRIPLE VIRAL (S...)": {
        "unidad": 0,
        "almacen": 13375,
        "total": 13375
      }
    }
  },
  "Direccion UMF 28": {
    "zona": "CARBONÍFERA",
    "vacunas": {
      "ANTIALACRAN": {
        "unidad": 2,
        "almacen": 252,
        "total": 254
      },
      "ANTIVIPERINO": {
        "unidad": 2,
        "almacen": 290,
        "total": 292
      },
      "BCG": {
        "unidad": 2,
        "almacen": 176,
        "total": 178
      },
      "DOBLE VIRAL (SR)": {
        "unidad": 0,
        "almacen": 60,
        "total": 60
      },
      "DPT": {
        "unidad": 15,
        "almacen": 578,
        "total": 593
      },
      "GAMA ANITETA...": {
        "unidad": 10,
        "almacen": 14,
        "total": 24
      },
      "GAMA ANITRA...": {
        "unidad": 12,
        "almacen": 1,
        "total": 13
      },
      "HEPATITIS A AD...": {
        "unidad": 2,
        "almacen": 64,
        "total": 66
      },
      "HEPATITIS B": {
        "unidad": 9,
        "almacen": 264,
        "total": 273
      },
      "HEXAVALENTE": {
        "unidad": 6,
        "almacen": 217,
        "total": 223
      },
      "NEUMO 13 V": {
        "unidad": 13,
        "almacen": 0,
        "total": 13
      },
      "NEUMO 20 V": {
        "unidad": 0,
        "almacen": 1620,
        "total": 1620
      },
      "NEUMO 23 V": {
        "unidad": 24,
        "almacen": 0,
        "total": 24
      },
      "ROTAVIRUS": {
        "unidad": 6,
        "almacen": 0,
        "total": 6
      },
      "TD": {
        "unidad": 38,
        "almacen": 0,
        "total": 38
      },
      "TDPA": {
        "unidad": 31,
        "almacen": 1144,
        "total": 1175
      },
      "TRIPLE VIRAL (S...)": {
        "unidad": 34,
        "almacen": 13375,
        "total": 13409
      },
      "VACUNA ANTIR...": {
        "unidad": 12,
        "almacen": 2,
        "total": 14
      },
      "VHP 9 V": {
        "unidad": 1,
        "almacen": 17,
        "total": 18
      },
      "VITAMINA A": {
        "unidad": 61,
        "almacen": 4755,
        "total": 4816
      }
    }
  },
  "Direccion UMF 29": {
    "zona": "CARBONÍFERA",
    "vacunas": {
      "ANTIALACRAN": {
        "unidad": 2,
        "almacen": 252,
        "total": 254
      },
      "ANTIARACNIDO F/I": {
        "unidad": 3,
        "almacen": 341,
        "total": 344
      },
      "BCG": {
        "unidad": 0,
        "almacen": 176,
        "total": 176
      },
      "DOBLE VIRAL (SR)": {
        "unidad": 0,
        "almacen": 60,
        "total": 60
      },
      "DPT": {
        "unidad": 0,
        "almacen": 578,
        "total": 578
      },
      "GAMA ANITETA...": {
        "unidad": 1,
        "almacen": 14,
        "total": 15
      },
      "GAMA ANITRA...": {
        "unidad": 8,
        "almacen": 1,
        "total": 9
      },
      "HEPATITIS A": {
        "unidad": 10,
        "almacen": 8,
        "total": 18
      },
      "HEPATITIS A AD...": {
        "unidad": 46,
        "almacen": 64,
        "total": 110
      },
      "HEPATITIS B": {
        "unidad": 0,
        "almacen": 264,
        "total": 264
      },
      "HEXAVALENTE": {
        "unidad": 0,
        "almacen": 217,
        "total": 217
      },
      "NEUMO 13 V": {
        "unidad": 0,
        "almacen": 0,
        "total": 0
      },
      "NEUMO 20 V": {
        "unidad": 0,
        "almacen": 1620,
        "total": 1620
      },
      "TD": {
        "unidad": 10,
        "almacen": 0,
        "total": 10
      },
      "TDPA": {
        "unidad": 0,
        "almacen": 1144,
        "total": 1144
      },
      "TRIPLE VIRAL (S...)": {
        "unidad": 0,
        "almacen": 13375,
        "total": 13375
      },
      "VITAMINA A": {
        "unidad": 0,
        "almacen": 4755,
        "total": 4755
      }
    }
  },
  "Direccion UMF 31": {
    "zona": "CARBONÍFERA",
    "vacunas": {
      "ANTIALACRAN": {
        "unidad": 0,
        "almacen": 252,
        "total": 252
      },
      "ANTIARACNIDO F/I": {
        "unidad": 0,
        "almacen": 341,
        "total": 341
      },
      "ANTIVIPERINO": {
        "unidad": 0,
        "almacen": 290,
        "total": 290
      },
      "BCG": {
        "unidad": 0,
        "almacen": 176,
        "total": 176
      },
      "COVID-19": {
        "unidad": 0,
        "almacen": 95,
        "total": 95
      },
      "DOBLE VIRAL (SR)": {
        "unidad": 0,
        "almacen": 60,
        "total": 60
      },
      "DPT": {
        "unidad": 0,
        "almacen": 578,
        "total": 578
      },
      "GAMA ANITETA...": {
        "unidad": 0,
        "almacen": 14,
        "total": 14
      },
      "GAMA ANITRA...": {
        "unidad": 0,
        "almacen": 1,
        "total": 1
      },
      "HEPATITIS B": {
        "unidad": 0,
        "almacen": 264,
        "total": 264
      },
      "HEXAVALENTE": {
        "unidad": 0,
        "almacen": 217,
        "total": 217
      },
      "INFLUENZA TET...": {
        "unidad": 0,
        "almacen": 0,
        "total": 0
      },
      "NEUMO 13 V": {
        "unidad": 0,
        "almacen": 0,
        "total": 0
      },
      "ROTAVIRUS": {
        "unidad": 0,
        "almacen": 0,
        "total": 0
      },
      "TD": {
        "unidad": 0,
        "almacen": 0,
        "total": 0
      },
      "TDPA": {
        "unidad": 0,
        "almacen": 1144,
        "total": 1144
      },
      "TRIPLE VIRAL (S...)": {
        "unidad": 0,
        "almacen": 13375,
        "total": 13375
      },
      "VACUNA ANTIR...": {
        "unidad": 0,
        "almacen": 2,
        "total": 2
      },
      "VHP 9 V": {
        "unidad": 0,
        "almacen": 17,
        "total": 17
      },
      "VITAMINA A": {
        "unidad": 0,
        "almacen": 4755,
        "total": 4755
      }
    }
  },
  "Direccion UMF 32": {
    "zona": "CARBONÍFERA",
    "vacunas": {
      "ANTIALACRAN": {
        "unidad": 4,
        "almacen": 252,
        "total": 256
      },
      "ANTIARACNIDO F/I": {
        "unidad": 2,
        "almacen": 341,
        "total": 343
      },
      "ANTIVIPERINO": {
        "unidad": 3,
        "almacen": 290,
        "total": 293
      },
      "BCG": {
        "unidad": 7,
        "almacen": 176,
        "total": 183
      },
      "DOBLE VIRAL (SR)": {
        "unidad": 22,
        "almacen": 60,
        "total": 82
      },
      "DPT": {
        "unidad": 20,
        "almacen": 578,
        "total": 598
      },
      "GAMA ANITRA...": {
        "unidad": 5,
        "almacen": 1,
        "total": 6
      },
      "HEPATITIS A": {
        "unidad": 10,
        "almacen": 8,
        "total": 18
      },
      "HEPATITIS A AD...": {
        "unidad": 0,
        "almacen": 64,
        "total": 64
      },
      "HEPATITIS B": {
        "unidad": 17,
        "almacen": 264,
        "total": 281
      },
      "HEXAVALENTE": {
        "unidad": 17,
        "almacen": 217,
        "total": 234
      },
      "NEUMO 13 V": {
        "unidad": 32,
        "almacen": 0,
        "total": 32
      },
      "NEUMO 20 V": {
        "unidad": 0,
        "almacen": 1620,
        "total": 1620
      },
      "NEUMO 23 V": {
        "unidad": 27,
        "almacen": 0,
        "total": 27
      },
      "ROTAVIRUS": {
        "unidad": 36,
        "almacen": 0,
        "total": 36
      },
      "TD": {
        "unidad": 35,
        "almacen": 0,
        "total": 35
      },
      "TDPA": {
        "unidad": 4,
        "almacen": 1144,
        "total": 1148
      },
      "TRIPLE VIRAL (S...)": {
        "unidad": 39,
        "almacen": 13375,
        "total": 13414
      }
    }
  },
  "Farmacia HGSZ-MF 27": {
    "zona": "CARBONÍFERA",
    "vacunas": {
      "BCG": {
        "unidad": 22,
        "almacen": 176,
        "total": 198
      },
      "COVID-19": {
        "unidad": 32,
        "almacen": 95,
        "total": 127
      },
      "DOBLE VIRAL (SR)": {
        "unidad": 151,
        "almacen": 60,
        "total": 211
      },
      "DPT": {
        "unidad": 23,
        "almacen": 578,
        "total": 601
      },
      "GAMA ANITRA...": {
        "unidad": 5,
        "almacen": 1,
        "total": 6
      },
      "HEPATITIS A": {
        "unidad": 2,
        "almacen": 8,
        "total": 10
      },
      "HEPATITIS A AD...": {
        "unidad": 9,
        "almacen": 64,
        "total": 73
      },
      "HEPATITIS B": {
        "unidad": 150,
        "almacen": 264,
        "total": 414
      },
      "HEXAVALENTE": {
        "unidad": 41,
        "almacen": 217,
        "total": 258
      },
      "INFLUENZA TET...": {
        "unidad": 17,
        "almacen": 0,
        "total": 17
      },
      "NEUMO 13 V": {
        "unidad": 10,
        "almacen": 0,
        "total": 10
      },
      "NEUMO 20 V": {
        "unidad": 280,
        "almacen": 1620,
        "total": 1900
      },
      "ROTAVIRUS": {
        "unidad": 3,
        "almacen": 0,
        "total": 3
      },
      "TDPA": {
        "unidad": 183,
        "almacen": 1144,
        "total": 1327
      },
      "TRIPLE VIRAL (S...)": {
        "unidad": 4090,
        "almacen": 13375,
        "total": 17465
      },
      "VACUNA ANTIR...": {
        "unidad": 3,
        "almacen": 2,
        "total": 5
      }
    }
  },
  "Farmacia HGZ-MF 24": {
    "zona": "CARBONÍFERA",
    "vacunas": {
      "ANTIALACRAN": {
        "unidad": 0,
        "almacen": 252,
        "total": 252
      },
      "ANTIARACNIDO F/I": {
        "unidad": 0,
        "almacen": 341,
        "total": 341
      },
      "ANTIVIPERINO": {
        "unidad": 0,
        "almacen": 290,
        "total": 290
      },
      "BCG": {
        "unidad": 0,
        "almacen": 176,
        "total": 176
      },
      "COVID-19": {
        "unidad": 0,
        "almacen": 95,
        "total": 95
      },
      "DOBLE VIRAL (SR)": {
        "unidad": 0,
        "almacen": 60,
        "total": 60
      },
      "DPT": {
        "unidad": 0,
        "almacen": 578,
        "total": 578
      },
      "HEPATITIS A": {
        "unidad": 0,
        "almacen": 8,
        "total": 8
      },
      "HEPATITIS B": {
        "unidad": 0,
        "almacen": 264,
        "total": 264
      },
      "HEXAVALENTE": {
        "unidad": 0,
        "almacen": 217,
        "total": 217
      },
      "INFLUENZA TET...": {
        "unidad": 0,
        "almacen": 0,
        "total": 0
      },
      "NEUMO 13 V": {
        "unidad": 0,
        "almacen": 0,
        "total": 0
      },
      "NEUMO 23 V": {
        "unidad": 0,
        "almacen": 0,
        "total": 0
      },
      "ROTAVIRUS": {
        "unidad": 0,
        "almacen": 0,
        "total": 0
      },
      "TD": {
        "unidad": 0,
        "almacen": 0,
        "total": 0
      },
      "TDPA": {
        "unidad": 0,
        "almacen": 1144,
        "total": 1144
      },
      "TRIPLE VIRAL (S...)": {
        "unidad": 0,
        "almacen": 13375,
        "total": 13375
      },
      "VACUNA ANTIR...": {
        "unidad": 0,
        "almacen": 2,
        "total": 2
      },
      "VITAMINA A": {
        "unidad": 0,
        "almacen": 4755,
        "total": 4755
      }
    }
  },
  "Direccion UMF 10": {
    "zona": "CENTRO",
    "vacunas": {
      "BCG": {
        "unidad": 4,
        "almacen": 176,
        "total": 180
      },
      "COVID-19": {
        "unidad": 0,
        "almacen": 95,
        "total": 95
      },
      "DOBLE VIRAL (SR)": {
        "unidad": 15,
        "almacen": 60,
        "total": 75
      },
      "DPT": {
        "unidad": 32,
        "almacen": 578,
        "total": 610
      },
      "HEPATITIS A": {
        "unidad": 4,
        "almacen": 8,
        "total": 12
      },
      "HEPATITIS A AD...": {
        "unidad": 6,
        "almacen": 64,
        "total": 70
      },
      "HEPATITIS B": {
        "unidad": 10,
        "almacen": 264,
        "total": 274
      },
      "HEXAVALENTE": {
        "unidad": 20,
        "almacen": 217,
        "total": 237
      },
      "NEUMO 13 V": {
        "unidad": 0,
        "almacen": 0,
        "total": 0
      },
      "NEUMO 20 V": {
        "unidad": 36,
        "almacen": 1620,
        "total": 1656
      },
      "ROTAVIRUS": {
        "unidad": 5,
        "almacen": 0,
        "total": 5
      },
      "TDPA": {
        "unidad": 7,
        "almacen": 1144,
        "total": 1151
      },
      "TRIPLE VIRAL (S...)": {
        "unidad": 100,
        "almacen": 13375,
        "total": 13475
      },
      "VACUNA ANTIR...": {
        "unidad": 0,
        "almacen": 2,
        "total": 2
      }
    }
  },
  "Direccion UMF 50": {
    "zona": "CENTRO",
    "vacunas": {
      "BCG": {
        "unidad": 4,
        "almacen": 176,
        "total": 180
      },
      "DOBLE VIRAL (SR)": {
        "unidad": 23,
        "almacen": 60,
        "total": 83
      },
      "DPT": {
        "unidad": 6,
        "almacen": 578,
        "total": 584
      },
      "HEPATITIS A AD...": {
        "unidad": 3,
        "almacen": 64,
        "total": 67
      },
      "HEPATITIS B": {
        "unidad": 10,
        "almacen": 264,
        "total": 274
      },
      "HEXAVALENTE": {
        "unidad": 5,
        "almacen": 217,
        "total": 222
      },
      "NEUMO 20 V": {
        "unidad": 18,
        "almacen": 1620,
        "total": 1638
      },
      "ROTAVIRUS": {
        "unidad": 10,
        "almacen": 0,
        "total": 10
      },
      "TD": {
        "unidad": 3,
        "almacen": 0,
        "total": 3
      },
      "TDPA": {
        "unidad": 3,
        "almacen": 1144,
        "total": 1147
      },
      "TRIPLE VIRAL (S...)": {
        "unidad": 133,
        "almacen": 13375,
        "total": 13508
      }
    }
  },
  "Direccion UMF 74": {
    "zona": "CENTRO",
    "vacunas": {
      "ANTIVIPERINO": {
        "unidad": 1,
        "almacen": 290,
        "total": 291
      },
      "BCG": {
        "unidad": 0,
        "almacen": 176,
        "total": 176
      },
      "DOBLE VIRAL (SR)": {
        "unidad": 0,
        "almacen": 60,
        "total": 60
      },
      "DPT": {
        "unidad": 0,
        "almacen": 578,
        "total": 578
      },
      "HEPATITIS A AD...": {
        "unidad": 0,
        "almacen": 64,
        "total": 64
      },
      "HEPATITIS B": {
        "unidad": 0,
        "almacen": 264,
        "total": 264
      },
      "HEXAVALENTE": {
        "unidad": 0,
        "almacen": 217,
        "total": 217
      },
      "NEUMO 20 V": {
        "unidad": 0,
        "almacen": 1620,
        "total": 1620
      },
      "ROTAVIRUS": {
        "unidad": 0,
        "almacen": 0,
        "total": 0
      },
      "TDPA": {
        "unidad": 0,
        "almacen": 1144,
        "total": 1144
      },
      "TRIPLE VIRAL (S...)": {
        "unidad": 0,
        "almacen": 13375,
        "total": 13375
      },
      "VITAMINA A": {
        "unidad": 6,
        "almacen": 4755,
        "total": 4761
      }
    }
  },
  "Direccion UMF 8": {
    "zona": "CENTRO",
    "vacunas": {
      "BCG": {
        "unidad": 6,
        "almacen": 176,
        "total": 182
      },
      "COVID-19": {
        "unidad": 0,
        "almacen": 95,
        "total": 95
      },
      "DOBLE VIRAL (SR)": {
        "unidad": 15,
        "almacen": 60,
        "total": 75
      },
      "DPT": {
        "unidad": 32,
        "almacen": 578,
        "total": 610
      },
      "HEPATITIS A AD...": {
        "unidad": 13,
        "almacen": 64,
        "total": 77
      },
      "HEPATITIS B": {
        "unidad": 20,
        "almacen": 264,
        "total": 284
      },
      "HEXAVALENTE": {
        "unidad": 55,
        "almacen": 217,
        "total": 272
      },
      "INFLUENZA TET...": {
        "unidad": 0,
        "almacen": 0,
        "total": 0
      },
      "NEUMO 13 V": {
        "unidad": 5,
        "almacen": 0,
        "total": 5
      },
      "NEUMO 20 V": {
        "unidad": 90,
        "almacen": 1620,
        "total": 1710
      },
      "ROTAVIRUS": {
        "unidad": 17,
        "almacen": 0,
        "total": 17
      },
      "TDPA": {
        "unidad": 194,
        "almacen": 1144,
        "total": 1338
      },
      "TRIPLE VIRAL (S...)": {
        "unidad": 300,
        "almacen": 13375,
        "total": 13675
      },
      "VACUNA ANTIR...": {
        "unidad": 2,
        "almacen": 2,
        "total": 4
      },
      "VITAMINA A": {
        "unidad": 130,
        "almacen": 4755,
        "total": 4885
      }
    }
  },
  "Direccion UMF 84": {
    "zona": "CENTRO",
    "vacunas": {
      "ANTIALACRAN": {
        "unidad": 0,
        "almacen": 252,
        "total": 252
      },
      "ANTIARACNIDO F/I": {
        "unidad": 0,
        "almacen": 341,
        "total": 341
      },
      "ANTIVIPERINO": {
        "unidad": 0,
        "almacen": 290,
        "total": 290
      },
      "BCG": {
        "unidad": 0,
        "almacen": 176,
        "total": 176
      },
      "COVID-19": {
        "unidad": 0,
        "almacen": 95,
        "total": 95
      },
      "DOBLE VIRAL (SR)": {
        "unidad": 56,
        "almacen": 60,
        "total": 116
      },
      "DPT": {
        "unidad": 24,
        "almacen": 578,
        "total": 602
      },
      "GAMA ANITRA...": {
        "unidad": 5,
        "almacen": 1,
        "total": 6
      },
      "HEPATITIS A AD...": {
        "unidad": 0,
        "almacen": 64,
        "total": 64
      },
      "HEPATITIS B": {
        "unidad": 0,
        "almacen": 264,
        "total": 264
      },
      "HEXAVALENTE": {
        "unidad": 67,
        "almacen": 217,
        "total": 284
      },
      "INFLUENZA TET...": {
        "unidad": 30,
        "almacen": 0,
        "total": 30
      },
      "NEUMO 13 V": {
        "unidad": 10,
        "almacen": 0,
        "total": 10
      },
      "NEUMO 20 V": {
        "unidad": 0,
        "almacen": 1620,
        "total": 1620
      },
      "ROTAVIRUS": {
        "unidad": 6,
        "almacen": 0,
        "total": 6
      },
      "TD": {
        "unidad": 130,
        "almacen": 0,
        "total": 130
      },
      "TDPA": {
        "unidad": 83,
        "almacen": 1144,
        "total": 1227
      },
      "TRIPLE VIRAL (S...)": {
        "unidad": 530,
        "almacen": 13375,
        "total": 13905
      },
      "VACUNA ANTIR...": {
        "unidad": 23,
        "almacen": 2,
        "total": 25
      },
      "VHP 9 V": {
        "unidad": 14,
        "almacen": 17,
        "total": 31
      },
      "VITAMINA A": {
        "unidad": 135,
        "almacen": 4755,
        "total": 4890
      }
    }
  },
  "Direccion UMF 85": {
    "zona": "CENTRO",
    "vacunas": {
      "COVID-19": {
        "unidad": 0,
        "almacen": 95,
        "total": 95
      },
      "DOBLE VIRAL (SR)": {
        "unidad": 0,
        "almacen": 60,
        "total": 60
      },
      "HEPATITIS A": {
        "unidad": 0,
        "almacen": 8,
        "total": 8
      },
      "HEPATITIS A AD...": {
        "unidad": 0,
        "almacen": 64,
        "total": 64
      },
      "HEPATITIS B": {
        "unidad": 0,
        "almacen": 264,
        "total": 264
      },
      "HEXAVALENTE": {
        "unidad": 0,
        "almacen": 217,
        "total": 217
      },
      "INFLUENZA TET...": {
        "unidad": 0,
        "almacen": 0,
        "total": 0
      },
      "NEUMO 13 V": {
        "unidad": 0,
        "almacen": 0,
        "total": 0
      },
      "ROTAVIRUS": {
        "unidad": 0,
        "almacen": 0,
        "total": 0
      },
      "TDPA": {
        "unidad": 0,
        "almacen": 1144,
        "total": 1144
      },
      "TRIPLE VIRAL (S...)": {
        "unidad": 0,
        "almacen": 13375,
        "total": 13375
      },
      "VACUNA ANTIR...": {
        "unidad": 0,
        "almacen": 2,
        "total": 2
      },
      "VHP 9 V": {
        "unidad": 0,
        "almacen": 17,
        "total": 17
      }
    }
  },
  "Direccion UMF 86": {
    "zona": "CENTRO",
    "vacunas": {
      "BCG": {
        "unidad": 5,
        "almacen": 176,
        "total": 181
      },
      "COVID-19": {
        "unidad": 5,
        "almacen": 95,
        "total": 100
      },
      "DOBLE VIRAL (SR)": {
        "unidad": 225,
        "almacen": 60,
        "total": 285
      },
      "DPT": {
        "unidad": 48,
        "almacen": 578,
        "total": 626
      },
      "HEPATITIS A": {
        "unidad": 24,
        "almacen": 8,
        "total": 32
      },
      "HEPATITIS A AD...": {
        "unidad": 13,
        "almacen": 64,
        "total": 77
      },
      "HEPATITIS B": {
        "unidad": 20,
        "almacen": 264,
        "total": 284
      },
      "HEXAVALENTE": {
        "unidad": 60,
        "almacen": 217,
        "total": 277
      },
      "INFLUENZA TET...": {
        "unidad": 30,
        "almacen": 0,
        "total": 30
      },
      "NEUMO 13 V": {
        "unidad": 10,
        "almacen": 0,
        "total": 10
      },
      "NEUMO 20 V": {
        "unidad": 72,
        "almacen": 1620,
        "total": 1692
      },
      "ROTAVIRUS": {
        "unidad": 16,
        "almacen": 0,
        "total": 16
      },
      "TDPA": {
        "unidad": 134,
        "almacen": 1144,
        "total": 1278
      },
      "TRIPLE VIRAL (S...)": {
        "unidad": 1290,
        "almacen": 13375,
        "total": 14665
      },
      "VACUNA ANTIR...": {
        "unidad": 6,
        "almacen": 2,
        "total": 8
      },
      "VITAMINA A": {
        "unidad": 40,
        "almacen": 4755,
        "total": 4795
      }
    }
  },
  "Direccion UMF 9": {
    "zona": "CENTRO",
    "vacunas": {
      "ANTIALACRAN": {
        "unidad": 15,
        "almacen": 252,
        "total": 267
      },
      "ANTIARACNIDO F/I": {
        "unidad": 10,
        "almacen": 341,
        "total": 351
      },
      "ANTIVIPERINO": {
        "unidad": 5,
        "almacen": 290,
        "total": 295
      },
      "BCG": {
        "unidad": 35,
        "almacen": 176,
        "total": 211
      },
      "COVID-19": {
        "unidad": 110,
        "almacen": 95,
        "total": 205
      },
      "DOBLE VIRAL (SR)": {
        "unidad": 282,
        "almacen": 60,
        "total": 342
      },
      "DPT": {
        "unidad": 99,
        "almacen": 578,
        "total": 677
      },
      "HEPATITIS A": {
        "unidad": 28,
        "almacen": 8,
        "total": 36
      },
      "HEPATITIS A AD...": {
        "unidad": 34,
        "almacen": 64,
        "total": 98
      },
      "HEPATITIS B": {
        "unidad": 40,
        "almacen": 264,
        "total": 304
      },
      "HEXAVALENTE": {
        "unidad": 143,
        "almacen": 217,
        "total": 360
      },
      "INFLUENZA TET...": {
        "unidad": 19,
        "almacen": 0,
        "total": 19
      },
      "NEUMO 13 V": {
        "unidad": 155,
        "almacen": 0,
        "total": 155
      },
      "NEUMO 20 V": {
        "unidad": 108,
        "almacen": 1620,
        "total": 1728
      },
      "ROTAVIRUS": {
        "unidad": 35,
        "almacen": 0,
        "total": 35
      },
      "TD": {
        "unidad": 40,
        "almacen": 0,
        "total": 40
      },
      "TDPA": {
        "unidad": 185,
        "almacen": 1144,
        "total": 1329
      },
      "TRIPLE VIRAL (S...)": {
        "unidad": 1105,
        "almacen": 13375,
        "total": 14480
      },
      "VACUNA ANTIR...": {
        "unidad": 3,
        "almacen": 2,
        "total": 5
      },
      "VHP 9 V": {
        "unidad": 15,
        "almacen": 17,
        "total": 32
      },
      "VITAMINA A": {
        "unidad": 180,
        "almacen": 4755,
        "total": 4935
      }
    }
  },
  "Farmacia HGZ-MF 7": {
    "zona": "CENTRO",
    "vacunas": {
      "ANTIALACRAN": {
        "unidad": 10,
        "almacen": 252,
        "total": 262
      },
      "ANTIARACNIDO F/I": {
        "unidad": 0,
        "almacen": 341,
        "total": 341
      },
      "ANTICORALILLO": {
        "unidad": 2,
        "almacen": 1,
        "total": 3
      },
      "ANTIVIPERINO": {
        "unidad": 0,
        "almacen": 290,
        "total": 290
      },
      "BCG": {
        "unidad": 20,
        "almacen": 176,
        "total": 196
      },
      "COVID-19": {
        "unidad": 9,
        "almacen": 95,
        "total": 104
      },
      "DOBLE VIRAL (SR)": {
        "unidad": 1224,
        "almacen": 60,
        "total": 1284
      },
      "DPT": {
        "unidad": 82,
        "almacen": 578,
        "total": 660
      },
      "GAMA ANITETA...": {
        "unidad": 0,
        "almacen": 14,
        "total": 14
      },
      "HEPATITIS A": {
        "unidad": 248,
        "almacen": 8,
        "total": 256
      },
      "HEPATITIS A AD...": {
        "unidad": 4,
        "almacen": 64,
        "total": 68
      },
      "HEPATITIS B": {
        "unidad": 156,
        "almacen": 264,
        "total": 420
      },
      "HEXAVALENTE": {
        "unidad": 115,
        "almacen": 217,
        "total": 332
      },
      "INFLUENZA TET...": {
        "unidad": 18,
        "almacen": 0,
        "total": 18
      },
      "NEUMO 13 V": {
        "unidad": 0,
        "almacen": 0,
        "total": 0
      },
      "NEUMO 20 V": {
        "unidad": 108,
        "almacen": 1620,
        "total": 1728
      },
      "ROTAVIRUS": {
        "unidad": 30,
        "almacen": 0,
        "total": 30
      },
      "TD": {
        "unidad": 0,
        "almacen": 0,
        "total": 0
      },
      "TDPA": {
        "unidad": 185,
        "almacen": 1144,
        "total": 1329
      },
      "TRIPLE VIRAL (S...)": {
        "unidad": 7005,
        "almacen": 13375,
        "total": 20380
      },
      "VACUNA ANTIR...": {
        "unidad": 10,
        "almacen": 2,
        "total": 12
      },
      "VITAMINA A": {
        "unidad": 230,
        "almacen": 4755,
        "total": 4985
      }
    }
  },
  "Farmacia HRS San Buenaventura": {
    "zona": "CENTRO",
    "vacunas": {
      "INFLUENZA TET...": {
        "unidad": 45,
        "almacen": 0,
        "total": 45
      }
    }
  },
  "Direccion UMF 61": {
    "zona": "LAGUNA",
    "vacunas": {
      "ANTIALACRAN": {
        "unidad": 5,
        "almacen": 252,
        "total": 257
      },
      "ANTIARACNIDO F/I": {
        "unidad": 10,
        "almacen": 341,
        "total": 351
      },
      "ANTIVIPERINO": {
        "unidad": 5,
        "almacen": 290,
        "total": 295
      },
      "BCG": {
        "unidad": 1,
        "almacen": 176,
        "total": 177
      },
      "DOBLE VIRAL (SR)": {
        "unidad": 66,
        "almacen": 60,
        "total": 126
      },
      "DPT": {
        "unidad": 1,
        "almacen": 578,
        "total": 579
      },
      "HEPATITIS B": {
        "unidad": 5,
        "almacen": 264,
        "total": 269
      },
      "HEXAVALENTE": {
        "unidad": 26,
        "almacen": 217,
        "total": 243
      },
      "NEUMO 13 V": {
        "unidad": 28,
        "almacen": 0,
        "total": 28
      },
      "NEUMO 23 V": {
        "unidad": 15,
        "almacen": 0,
        "total": 15
      },
      "ROTAVIRUS": {
        "unidad": 6,
        "almacen": 0,
        "total": 6
      },
      "TD": {
        "unidad": 10,
        "almacen": 0,
        "total": 10
      },
      "TDPA": {
        "unidad": 32,
        "almacen": 1144,
        "total": 1176
      },
      "TRIPLE VIRAL (S...)": {
        "unidad": 102,
        "almacen": 13375,
        "total": 13477
      },
      "VHP 9 V": {
        "unidad": 5,
        "almacen": 17,
        "total": 22
      },
      "VITAMINA A": {
        "unidad": 20,
        "almacen": 4755,
        "total": 4775
      }
    }
  },
  "Direccion UMF 80": {
    "zona": "LAGUNA",
    "vacunas": {
      "ANTIARACNIDO F/I": {
        "unidad": 0,
        "almacen": 341,
        "total": 341
      },
      "ANTIVIPERINO": {
        "unidad": 10,
        "almacen": 290,
        "total": 300
      },
      "BCG": {
        "unidad": 22,
        "almacen": 176,
        "total": 198
      },
      "COVID-19": {
        "unidad": 0,
        "almacen": 95,
        "total": 95
      },
      "DOBLE VIRAL (SR)": {
        "unidad": 15,
        "almacen": 60,
        "total": 75
      },
      "DPT": {
        "unidad": 68,
        "almacen": 578,
        "total": 646
      },
      "GAMA ANITRA...": {
        "unidad": 0,
        "almacen": 1,
        "total": 1
      },
      "HEPATITIS A AD...": {
        "unidad": 7,
        "almacen": 64,
        "total": 71
      },
      "HEPATITIS B": {
        "unidad": 75,
        "almacen": 264,
        "total": 339
      },
      "HEXAVALENTE": {
        "unidad": 60,
        "almacen": 217,
        "total": 277
      },
      "INFLUENZA TET...": {
        "unidad": 0,
        "almacen": 0,
        "total": 0
      },
      "NEUMO 13 V": {
        "unidad": 0,
        "almacen": 0,
        "total": 0
      },
      "NEUMO 20 V": {
        "unidad": 400,
        "almacen": 1620,
        "total": 2020
      },
      "ROTAVIRUS": {
        "unidad": 10,
        "almacen": 0,
        "total": 10
      },
      "TD": {
        "unidad": 0,
        "almacen": 0,
        "total": 0
      },
      "TDPA": {
        "unidad": 349,
        "almacen": 1144,
        "total": 1493
      },
      "TRIPLE VIRAL (S...)": {
        "unidad": 1100,
        "almacen": 13375,
        "total": 14475
      },
      "VACUNA ANTIR...": {
        "unidad": 0,
        "almacen": 2,
        "total": 2
      },
      "VHP 9 V": {
        "unidad": 1,
        "almacen": 17,
        "total": 18
      },
      "VITAMINA A": {
        "unidad": 125,
        "almacen": 4755,
        "total": 4880
      }
    }
  },
  "Direccion UMF 83": {
    "zona": "LAGUNA",
    "vacunas": {
      "ANTIALACRAN": {
        "unidad": 3,
        "almacen": 252,
        "total": 255
      },
      "ANTIARACNIDO F/I": {
        "unidad": 9,
        "almacen": 341,
        "total": 350
      },
      "ANTIVIPERINO": {
        "unidad": 25,
        "almacen": 290,
        "total": 315
      },
      "BCG": {
        "unidad": 46,
        "almacen": 176,
        "total": 222
      },
      "COVID-19": {
        "unidad": 51,
        "almacen": 95,
        "total": 146
      },
      "DOBLE VIRAL (SR)": {
        "unidad": 107,
        "almacen": 60,
        "total": 167
      },
      "DPT": {
        "unidad": 116,
        "almacen": 578,
        "total": 694
      },
      "GAMA ANITETA...": {
        "unidad": 10,
        "almacen": 14,
        "total": 24
      },
      "GAMA ANITRA...": {
        "unidad": 10,
        "almacen": 1,
        "total": 11
      },
      "HEPATITIS A AD...": {
        "unidad": 4,
        "almacen": 64,
        "total": 68
      },
      "HEPATITIS B": {
        "unidad": 63,
        "almacen": 264,
        "total": 327
      },
      "HEXAVALENTE": {
        "unidad": 35,
        "almacen": 217,
        "total": 252
      },
      "INFLUENZA TET...": {
        "unidad": 0,
        "almacen": 0,
        "total": 0
      },
      "NEUMO 13 V": {
        "unidad": 166,
        "almacen": 0,
        "total": 166
      },
      "NEUMO 23 V": {
        "unidad": 0,
        "almacen": 0,
        "total": 0
      },
      "ROTAVIRUS": {
        "unidad": 10,
        "almacen": 0,
        "total": 10
      },
      "TD": {
        "unidad": 379,
        "almacen": 0,
        "total": 379
      },
      "TDPA": {
        "unidad": 498,
        "almacen": 1144,
        "total": 1642
      },
      "TRIPLE VIRAL (S...)": {
        "unidad": 1950,
        "almacen": 13375,
        "total": 15325
      },
      "VACUNA ANTIR...": {
        "unidad": 22,
        "almacen": 2,
        "total": 24
      },
      "VARICELA": {
        "unidad": 0,
        "almacen": 0,
        "total": 0
      },
      "VHP 9 V": {
        "unidad": 25,
        "almacen": 17,
        "total": 42
      },
      "VITAMINA A": {
        "unidad": 500,
        "almacen": 4755,
        "total": 5255
      }
    }
  },
  "Direccion UMR-EM 52": {
    "zona": "LAGUNA",
    "vacunas": {
      "ANTIVIPERINO": {
        "unidad": 2,
        "almacen": 290,
        "total": 292
      },
      "BCG": {
        "unidad": 0,
        "almacen": 176,
        "total": 176
      },
      "DOBLE VIRAL (SR)": {
        "unidad": 0,
        "almacen": 60,
        "total": 60
      },
      "DPT": {
        "unidad": 2,
        "almacen": 578,
        "total": 580
      },
      "HEPATITIS A AD...": {
        "unidad": 0,
        "almacen": 64,
        "total": 64
      },
      "HEPATITIS B": {
        "unidad": 0,
        "almacen": 264,
        "total": 264
      },
      "HEXAVALENTE": {
        "unidad": 0,
        "almacen": 217,
        "total": 217
      },
      "NEUMO 20 V": {
        "unidad": 0,
        "almacen": 1620,
        "total": 1620
      },
      "ROTAVIRUS": {
        "unidad": 0,
        "almacen": 0,
        "total": 0
      },
      "TDPA": {
        "unidad": 0,
        "almacen": 1144,
        "total": 1144
      },
      "TRIPLE VIRAL (S...)": {
        "unidad": 3,
        "almacen": 13375,
        "total": 13378
      }
    }
  },
  "Farmacia HGSZ-MF 20": {
    "zona": "LAGUNA",
    "vacunas": {
      "COVID-19": {
        "unidad": 0,
        "almacen": 95,
        "total": 95
      },
      "DOBLE VIRAL (SR)": {
        "unidad": 0,
        "almacen": 60,
        "total": 60
      },
      "HEXAVALENTE": {
        "unidad": 0,
        "almacen": 217,
        "total": 217
      },
      "INFLUENZA TET...": {
        "unidad": 0,
        "almacen": 0,
        "total": 0
      },
      "TDPA": {
        "unidad": 0,
        "almacen": 1144,
        "total": 1144
      },
      "TRIPLE VIRAL (S...)": {
        "unidad": 0,
        "almacen": 13375,
        "total": 13375
      }
    }
  },
  "Farmacia HGSZ-MF 21": {
    "zona": "LAGUNA",
    "vacunas": {
      "ANTIVIPERINO": {
        "unidad": 5,
        "almacen": 290,
        "total": 295
      },
      "BCG": {
        "unidad": 0,
        "almacen": 176,
        "total": 176
      },
      "COVID-19": {
        "unidad": 1,
        "almacen": 95,
        "total": 96
      },
      "DOBLE VIRAL (SR)": {
        "unidad": 200,
        "almacen": 60,
        "total": 260
      },
      "DPT": {
        "unidad": 0,
        "almacen": 578,
        "total": 578
      },
      "HEPATITIS A AD...": {
        "unidad": 0,
        "almacen": 64,
        "total": 64
      },
      "HEPATITIS B": {
        "unidad": 0,
        "almacen": 264,
        "total": 264
      },
      "HEXAVALENTE": {
        "unidad": 13,
        "almacen": 217,
        "total": 230
      },
      "INFLUENZA TET...": {
        "unidad": 30,
        "almacen": 0,
        "total": 30
      },
      "NEUMO 20 V": {
        "unidad": 0,
        "almacen": 1620,
        "total": 1620
      },
      "ROTAVIRUS": {
        "unidad": 0,
        "almacen": 0,
        "total": 0
      },
      "TDPA": {
        "unidad": 200,
        "almacen": 1144,
        "total": 1344
      },
      "TRIPLE VIRAL (S...)": {
        "unidad": 4700,
        "almacen": 13375,
        "total": 18075
      }
    }
  },
  "Farmacia HGSZ-MF 6": {
    "zona": "LAGUNA",
    "vacunas": {
      "BCG": {
        "unidad": 0,
        "almacen": 176,
        "total": 176
      },
      "DOBLE VIRAL (SR)": {
        "unidad": 0,
        "almacen": 60,
        "total": 60
      },
      "DPT": {
        "unidad": 0,
        "almacen": 578,
        "total": 578
      },
      "HEPATITIS A AD...": {
        "unidad": 0,
        "almacen": 64,
        "total": 64
      },
      "HEPATITIS B": {
        "unidad": 0,
        "almacen": 264,
        "total": 264
      },
      "HEXAVALENTE": {
        "unidad": 0,
        "almacen": 217,
        "total": 217
      },
      "NEUMO 20 V": {
        "unidad": 0,
        "almacen": 1620,
        "total": 1620
      },
      "ROTAVIRUS": {
        "unidad": 0,
        "almacen": 0,
        "total": 0
      },
      "TDPA": {
        "unidad": 0,
        "almacen": 1144,
        "total": 1144
      },
      "TRIPLE VIRAL (S...)": {
        "unidad": 0,
        "almacen": 13375,
        "total": 13375
      }
    }
  },
  "Farmacia HGZ-MF 16": {
    "zona": "LAGUNA",
    "vacunas": {
      "ANTIALACRAN": {
        "unidad": 20,
        "almacen": 252,
        "total": 272
      },
      "ANTIARACNIDO F/I": {
        "unidad": 2,
        "almacen": 341,
        "total": 343
      },
      "ANTICORALILLO": {
        "unidad": 1,
        "almacen": 1,
        "total": 2
      },
      "ANTIVIPERINO": {
        "unidad": 73,
        "almacen": 290,
        "total": 363
      },
      "BCG": {
        "unidad": 50,
        "almacen": 176,
        "total": 226
      },
      "COVID-19": {
        "unidad": 54,
        "almacen": 95,
        "total": 149
      },
      "DOBLE VIRAL (SR)": {
        "unidad": 1430,
        "almacen": 60,
        "total": 1490
      },
      "DPT": {
        "unidad": 214,
        "almacen": 578,
        "total": 792
      },
      "GAMA ANITETA...": {
        "unidad": 34,
        "almacen": 14,
        "total": 48
      },
      "GAMA ANITRA...": {
        "unidad": 0,
        "almacen": 1,
        "total": 1
      },
      "HEPATITIS A": {
        "unidad": 0,
        "almacen": 8,
        "total": 8
      },
      "HEPATITIS A AD...": {
        "unidad": 129,
        "almacen": 64,
        "total": 193
      },
      "HEPATITIS B": {
        "unidad": 235,
        "almacen": 264,
        "total": 499
      },
      "HEXAVALENTE": {
        "unidad": 293,
        "almacen": 217,
        "total": 510
      },
      "INFLUENZA TET...": {
        "unidad": 20,
        "almacen": 0,
        "total": 20
      },
      "NEUMO 13 V": {
        "unidad": 0,
        "almacen": 0,
        "total": 0
      },
      "NEUMO 20 V": {
        "unidad": 600,
        "almacen": 1620,
        "total": 2220
      },
      "NEUMO 23 V": {
        "unidad": 0,
        "almacen": 0,
        "total": 0
      },
      "ROTAVIRUS": {
        "unidad": 15,
        "almacen": 0,
        "total": 15
      },
      "TD": {
        "unidad": 0,
        "almacen": 0,
        "total": 0
      },
      "TDPA": {
        "unidad": 689,
        "almacen": 1144,
        "total": 1833
      },
      "TRIPLE VIRAL (S...)": {
        "unidad": 10350,
        "almacen": 13375,
        "total": 23725
      },
      "VACUNA ANTIR...": {
        "unidad": 0,
        "almacen": 2,
        "total": 2
      },
      "VARICELA": {
        "unidad": 0,
        "almacen": 0,
        "total": 0
      },
      "VHP 9 V": {
        "unidad": 73,
        "almacen": 17,
        "total": 90
      },
      "VITAMINA A": {
        "unidad": 0,
        "almacen": 4755,
        "total": 4755
      }
    }
  },
  "Farmacia HGZ-MF 18": {
    "zona": "LAGUNA",
    "vacunas": {
      "ANTIALACRAN": {
        "unidad": 10,
        "almacen": 252,
        "total": 262
      },
      "ANTIARACNIDO F/I": {
        "unidad": 0,
        "almacen": 341,
        "total": 341
      },
      "ANTICORALILLO": {
        "unidad": 0,
        "almacen": 1,
        "total": 1
      },
      "ANTIVIPERINO": {
        "unidad": 0,
        "almacen": 290,
        "total": 290
      },
      "BCG": {
        "unidad": 30,
        "almacen": 176,
        "total": 206
      },
      "COVID-19": {
        "unidad": 14,
        "almacen": 95,
        "total": 109
      },
      "DOBLE VIRAL (SR)": {
        "unidad": 40,
        "almacen": 60,
        "total": 100
      },
      "DPT": {
        "unidad": 40,
        "almacen": 578,
        "total": 618
      },
      "GAMA ANITETA...": {
        "unidad": 0,
        "almacen": 14,
        "total": 14
      },
      "GAMA ANITRA...": {
        "unidad": 0,
        "almacen": 1,
        "total": 1
      },
      "HEPATITIS A": {
        "unidad": 0,
        "almacen": 8,
        "total": 8
      },
      "HEPATITIS A AD...": {
        "unidad": 6,
        "almacen": 64,
        "total": 70
      },
      "HEPATITIS B": {
        "unidad": 140,
        "almacen": 264,
        "total": 404
      },
      "HEXAVALENTE": {
        "unidad": 40,
        "almacen": 217,
        "total": 257
      },
      "INFLUENZA TET...": {
        "unidad": 0,
        "almacen": 0,
        "total": 0
      },
      "NEUMO 13 V": {
        "unidad": 0,
        "almacen": 0,
        "total": 0
      },
      "NEUMO 20 V": {
        "unidad": 400,
        "almacen": 1620,
        "total": 2020
      },
      "NEUMO 23 V": {
        "unidad": 0,
        "almacen": 0,
        "total": 0
      },
      "ROTAVIRUS": {
        "unidad": 10,
        "almacen": 0,
        "total": 10
      },
      "TD": {
        "unidad": 0,
        "almacen": 0,
        "total": 0
      },
      "TDPA": {
        "unidad": 28,
        "almacen": 1144,
        "total": 1172
      },
      "TRIPLE VIRAL (S...)": {
        "unidad": 8300,
        "almacen": 13375,
        "total": 21675
      },
      "VACUNA ANTIR...": {
        "unidad": 0,
        "almacen": 2,
        "total": 2
      },
      "VARICELA": {
        "unidad": 0,
        "almacen": 0,
        "total": 0
      },
      "VHP 9 V": {
        "unidad": 0,
        "almacen": 17,
        "total": 17
      },
      "VITAMINA A": {
        "unidad": 0,
        "almacen": 4755,
        "total": 4755
      }
    }
  },
  "Farmacia UMF 66": {
    "zona": "LAGUNA",
    "vacunas": {
      "BCG": {
        "unidad": 46,
        "almacen": 176,
        "total": 222
      },
      "COVID-19": {
        "unidad": 0,
        "almacen": 95,
        "total": 95
      },
      "DOBLE VIRAL (SR)": {
        "unidad": 40,
        "almacen": 60,
        "total": 100
      },
      "DPT": {
        "unidad": 180,
        "almacen": 578,
        "total": 758
      },
      "HEPATITIS A": {
        "unidad": 0,
        "almacen": 8,
        "total": 8
      },
      "HEPATITIS A AD...": {
        "unidad": 10,
        "almacen": 64,
        "total": 74
      },
      "HEPATITIS B": {
        "unidad": 150,
        "almacen": 264,
        "total": 414
      },
      "HEXAVALENTE": {
        "unidad": 31,
        "almacen": 217,
        "total": 248
      },
      "INFLUENZA TET...": {
        "unidad": 0,
        "almacen": 0,
        "total": 0
      },
      "NEUMO 13 V": {
        "unidad": 0,
        "almacen": 0,
        "total": 0
      },
      "NEUMO 20 V": {
        "unidad": 600,
        "almacen": 1620,
        "total": 2220
      },
      "ROTAVIRUS": {
        "unidad": 0,
        "almacen": 0,
        "total": 0
      },
      "TDPA": {
        "unidad": 0,
        "almacen": 1144,
        "total": 1144
      },
      "TRIPLE VIRAL (S...)": {
        "unidad": 5000,
        "almacen": 13375,
        "total": 18375
      },
      "VACUNA ANTIR...": {
        "unidad": 3,
        "almacen": 2,
        "total": 5
      },
      "VITAMINA A": {
        "unidad": 0,
        "almacen": 4755,
        "total": 4755
      }
    }
  },
  "Farmacia UMF 93": {
    "zona": "LAGUNA",
    "vacunas": {
      "ANTIALACRAN": {
        "unidad": 0,
        "almacen": 252,
        "total": 252
      },
      "ANTIARACNIDO F/I": {
        "unidad": 0,
        "almacen": 341,
        "total": 341
      },
      "ANTIVIPERINO": {
        "unidad": 12,
        "almacen": 290,
        "total": 302
      },
      "BCG": {
        "unidad": 120,
        "almacen": 176,
        "total": 296
      },
      "COVID-19": {
        "unidad": 5,
        "almacen": 95,
        "total": 100
      },
      "DOBLE VIRAL (SR)": {
        "unidad": 20,
        "almacen": 60,
        "total": 80
      },
      "DPT": {
        "unidad": 48,
        "almacen": 578,
        "total": 626
      },
      "GAMA ANITETA...": {
        "unidad": 0,
        "almacen": 14,
        "total": 14
      },
      "GAMA ANITRA...": {
        "unidad": 0,
        "almacen": 1,
        "total": 1
      },
      "HEPATITIS A AD...": {
        "unidad": 5,
        "almacen": 64,
        "total": 69
      },
      "HEPATITIS B": {
        "unidad": 60,
        "almacen": 264,
        "total": 324
      },
      "HEXAVALENTE": {
        "unidad": 60,
        "almacen": 217,
        "total": 277
      },
      "INFLUENZA TET...": {
        "unidad": 0,
        "almacen": 0,
        "total": 0
      },
      "NEUMO 13 V": {
        "unidad": 0,
        "almacen": 0,
        "total": 0
      },
      "NEUMO 20 V": {
        "unidad": 400,
        "almacen": 1620,
        "total": 2020
      },
      "NEUMO 23 V": {
        "unidad": 0,
        "almacen": 0,
        "total": 0
      },
      "ROTAVIRUS": {
        "unidad": 11,
        "almacen": 0,
        "total": 11
      },
      "TD": {
        "unidad": 0,
        "almacen": 0,
        "total": 0
      },
      "TDPA": {
        "unidad": 311,
        "almacen": 1144,
        "total": 1455
      },
      "TRIPLE VIRAL (S...)": {
        "unidad": 2000,
        "almacen": 13375,
        "total": 15375
      },
      "VACUNA ANTIR...": {
        "unidad": 6,
        "almacen": 2,
        "total": 8
      },
      "VHP 9 V": {
        "unidad": 24,
        "almacen": 17,
        "total": 41
      },
      "VITAMINA A": {
        "unidad": 300,
        "almacen": 4755,
        "total": 5055
      }
    }
  },
  "Direccion UMF 12": {
    "zona": "NORTE",
    "vacunas": {
      "ANTIALACRAN": {
        "unidad": 10,
        "almacen": 252,
        "total": 262
      },
      "ANTIARACNIDO F/I": {
        "unidad": 10,
        "almacen": 341,
        "total": 351
      },
      "ANTIVIPERINO": {
        "unidad": 5,
        "almacen": 290,
        "total": 295
      },
      "BCG": {
        "unidad": 6,
        "almacen": 176,
        "total": 182
      },
      "COVID-19": {
        "unidad": 5,
        "almacen": 95,
        "total": 100
      },
      "DOBLE VIRAL (SR)": {
        "unidad": 130,
        "almacen": 60,
        "total": 190
      },
      "DPT": {
        "unidad": 0,
        "almacen": 578,
        "total": 578
      },
      "GAMA ANITETA...": {
        "unidad": 0,
        "almacen": 14,
        "total": 14
      },
      "GAMA ANITRA...": {
        "unidad": 4,
        "almacen": 1,
        "total": 5
      },
      "HEPATITIS A AD...": {
        "unidad": 20,
        "almacen": 64,
        "total": 84
      },
      "HEPATITIS B": {
        "unidad": 7,
        "almacen": 264,
        "total": 271
      },
      "HEXAVALENTE": {
        "unidad": 20,
        "almacen": 217,
        "total": 237
      },
      "INFLUENZA TET...": {
        "unidad": 0,
        "almacen": 0,
        "total": 0
      },
      "NEUMO 13 V": {
        "unidad": 15,
        "almacen": 0,
        "total": 15
      },
      "NEUMO 20 V": {
        "unidad": 18,
        "almacen": 1620,
        "total": 1638
      },
      "NEUMO 23 V": {
        "unidad": 0,
        "almacen": 0,
        "total": 0
      },
      "ROTAVIRUS": {
        "unidad": 13,
        "almacen": 0,
        "total": 13
      },
      "TD": {
        "unidad": 0,
        "almacen": 0,
        "total": 0
      },
      "TDPA": {
        "unidad": 155,
        "almacen": 1144,
        "total": 1299
      },
      "TRIPLE VIRAL (S...)": {
        "unidad": 200,
        "almacen": 13375,
        "total": 13575
      },
      "VACUNA ANTIR...": {
        "unidad": 16,
        "almacen": 2,
        "total": 18
      },
      "VHP 9 V": {
        "unidad": 0,
        "almacen": 17,
        "total": 17
      },
      "VITAMINA A": {
        "unidad": 0,
        "almacen": 4755,
        "total": 4755
      }
    }
  },
  "Direccion UMF 14": {
    "zona": "NORTE",
    "vacunas": {
      "BCG": {
        "unidad": 0,
        "almacen": 176,
        "total": 176
      },
      "DOBLE VIRAL (SR)": {
        "unidad": 10,
        "almacen": 60,
        "total": 70
      },
      "HEPATITIS A AD...": {
        "unidad": 6,
        "almacen": 64,
        "total": 70
      },
      "HEPATITIS B": {
        "unidad": 1,
        "almacen": 264,
        "total": 265
      },
      "HEXAVALENTE": {
        "unidad": 8,
        "almacen": 217,
        "total": 225
      },
      "NEUMO 13 V": {
        "unidad": 11,
        "almacen": 0,
        "total": 11
      },
      "NEUMO 20 V": {
        "unidad": 0,
        "almacen": 1620,
        "total": 1620
      },
      "ROTAVIRUS": {
        "unidad": 1,
        "almacen": 0,
        "total": 1
      },
      "TDPA": {
        "unidad": 8,
        "almacen": 1144,
        "total": 1152
      },
      "TRIPLE VIRAL (S...)": {
        "unidad": 169,
        "almacen": 13375,
        "total": 13544
      },
      "VACUNA ANTIR...": {
        "unidad": 2,
        "almacen": 2,
        "total": 4
      }
    }
  },
  "Direccion UMF 15": {
    "zona": "NORTE",
    "vacunas": {
      "ANTIALACRAN": {
        "unidad": 6,
        "almacen": 252,
        "total": 258
      },
      "ANTIARACNIDO F/I": {
        "unidad": 1,
        "almacen": 341,
        "total": 342
      },
      "ANTIVIPERINO": {
        "unidad": 6,
        "almacen": 290,
        "total": 296
      },
      "BCG": {
        "unidad": 16,
        "almacen": 176,
        "total": 192
      },
      "COVID-19": {
        "unidad": 19,
        "almacen": 95,
        "total": 114
      },
      "DOBLE VIRAL (SR)": {
        "unidad": 20,
        "almacen": 60,
        "total": 80
      },
      "DPT": {
        "unidad": 12,
        "almacen": 578,
        "total": 590
      },
      "GAMA ANITETA...": {
        "unidad": 4,
        "almacen": 14,
        "total": 18
      },
      "GAMA ANITRA...": {
        "unidad": 4,
        "almacen": 1,
        "total": 5
      },
      "HEPATITIS A AD...": {
        "unidad": 5,
        "almacen": 64,
        "total": 69
      },
      "HEPATITIS B": {
        "unidad": 11,
        "almacen": 264,
        "total": 275
      },
      "HEXAVALENTE": {
        "unidad": 65,
        "almacen": 217,
        "total": 282
      },
      "INFLUENZA TET...": {
        "unidad": 31,
        "almacen": 0,
        "total": 31
      },
      "NEUMO 13 V": {
        "unidad": 61,
        "almacen": 0,
        "total": 61
      },
      "NEUMO 20 V": {
        "unidad": 18,
        "almacen": 1620,
        "total": 1638
      },
      "NEUMO 23 V": {
        "unidad": 180,
        "almacen": 0,
        "total": 180
      },
      "ROTAVIRUS": {
        "unidad": 9,
        "almacen": 0,
        "total": 9
      },
      "TD": {
        "unidad": 9,
        "almacen": 0,
        "total": 9
      },
      "TDPA": {
        "unidad": 34,
        "almacen": 1144,
        "total": 1178
      },
      "TRIPLE VIRAL (S...)": {
        "unidad": 200,
        "almacen": 13375,
        "total": 13575
      },
      "VACUNA ANTIR...": {
        "unidad": 15,
        "almacen": 2,
        "total": 17
      },
      "VHP 9 V": {
        "unidad": 7,
        "almacen": 17,
        "total": 24
      },
      "VITAMINA A": {
        "unidad": 151,
        "almacen": 4755,
        "total": 4906
      }
    }
  },
  "Direccion UMF 60": {
    "zona": "NORTE",
    "vacunas": {
      "BCG": {
        "unidad": 0,
        "almacen": 176,
        "total": 176
      },
      "DOBLE VIRAL (SR)": {
        "unidad": 0,
        "almacen": 60,
        "total": 60
      },
      "HEPATITIS A AD...": {
        "unidad": 0,
        "almacen": 64,
        "total": 64
      },
      "HEPATITIS B": {
        "unidad": 0,
        "almacen": 264,
        "total": 264
      },
      "HEXAVALENTE": {
        "unidad": 0,
        "almacen": 217,
        "total": 217
      },
      "NEUMO 20 V": {
        "unidad": 0,
        "almacen": 1620,
        "total": 1620
      },
      "ROTAVIRUS": {
        "unidad": 0,
        "almacen": 0,
        "total": 0
      },
      "TDPA": {
        "unidad": 0,
        "almacen": 1144,
        "total": 1144
      },
      "TRIPLE VIRAL (S...)": {
        "unidad": 0,
        "almacen": 13375,
        "total": 13375
      }
    }
  },
  "Direccion UMF 64": {
    "zona": "NORTE",
    "vacunas": {
      "BCG": {
        "unidad": 0,
        "almacen": 176,
        "total": 176
      },
      "DOBLE VIRAL (SR)": {
        "unidad": 3,
        "almacen": 60,
        "total": 63
      },
      "DPT": {
        "unidad": 1,
        "almacen": 578,
        "total": 579
      },
      "HEPATITIS A AD...": {
        "unidad": 0,
        "almacen": 64,
        "total": 64
      },
      "HEPATITIS B": {
        "unidad": 5,
        "almacen": 264,
        "total": 269
      },
      "HEXAVALENTE": {
        "unidad": 0,
        "almacen": 217,
        "total": 217
      },
      "NEUMO 20 V": {
        "unidad": 0,
        "almacen": 1620,
        "total": 1620
      },
      "ROTAVIRUS": {
        "unidad": 25,
        "almacen": 0,
        "total": 25
      },
      "TD": {
        "unidad": 6,
        "almacen": 0,
        "total": 6
      },
      "TDPA": {
        "unidad": 12,
        "almacen": 1144,
        "total": 1156
      },
      "TRIPLE VIRAL (S...)": {
        "unidad": 25,
        "almacen": 13375,
        "total": 13400
      },
      "VARICELA": {
        "unidad": 5,
        "almacen": 0,
        "total": 5
      },
      "VITAMINA A": {
        "unidad": 203,
        "almacen": 4755,
        "total": 4958
      }
    }
  },
  "Direccion UMF 81": {
    "zona": "NORTE",
    "vacunas": {
      "ANTIVIPERINO": {
        "unidad": 0,
        "almacen": 290,
        "total": 290
      },
      "BCG": {
        "unidad": 24,
        "almacen": 176,
        "total": 200
      },
      "COVID-19": {
        "unidad": 0,
        "almacen": 95,
        "total": 95
      },
      "DOBLE VIRAL (SR)": {
        "unidad": 426,
        "almacen": 60,
        "total": 486
      },
      "HEPATITIS A": {
        "unidad": 174,
        "almacen": 8,
        "total": 182
      },
      "HEPATITIS A AD...": {
        "unidad": 50,
        "almacen": 64,
        "total": 114
      },
      "HEPATITIS B": {
        "unidad": 50,
        "almacen": 264,
        "total": 314
      },
      "HEXAVALENTE": {
        "unidad": 0,
        "almacen": 217,
        "total": 217
      },
      "INFLUENZA TET...": {
        "unidad": 0,
        "almacen": 0,
        "total": 0
      },
      "NEUMO 13 V": {
        "unidad": 0,
        "almacen": 0,
        "total": 0
      },
      "NEUMO 20 V": {
        "unidad": 0,
        "almacen": 1620,
        "total": 1620
      },
      "ROTAVIRUS": {
        "unidad": 6,
        "almacen": 0,
        "total": 6
      },
      "TDPA": {
        "unidad": 921,
        "almacen": 1144,
        "total": 2065
      },
      "TRIPLE VIRAL (S...)": {
        "unidad": 1350,
        "almacen": 13375,
        "total": 14725
      }
    }
  },
  "Direccion UMF 87": {
    "zona": "NORTE",
    "vacunas": {
      "ANTIALACRAN": {
        "unidad": 0,
        "almacen": 252,
        "total": 252
      },
      "ANTIARACNIDO F/I": {
        "unidad": 0,
        "almacen": 341,
        "total": 341
      },
      "ANTIVIPERINO": {
        "unidad": 0,
        "almacen": 290,
        "total": 290
      },
      "COVID-19": {
        "unidad": 1,
        "almacen": 95,
        "total": 96
      },
      "DOBLE VIRAL (SR)": {
        "unidad": 0,
        "almacen": 60,
        "total": 60
      },
      "HEPATITIS A": {
        "unidad": 50,
        "almacen": 8,
        "total": 58
      },
      "HEPATITIS A AD...": {
        "unidad": 0,
        "almacen": 64,
        "total": 64
      },
      "HEPATITIS B": {
        "unidad": 0,
        "almacen": 264,
        "total": 264
      },
      "HEXAVALENTE": {
        "unidad": 0,
        "almacen": 217,
        "total": 217
      },
      "INFLUENZA TET...": {
        "unidad": 60,
        "almacen": 0,
        "total": 60
      },
      "NEUMO 13 V": {
        "unidad": 0,
        "almacen": 0,
        "total": 0
      },
      "ROTAVIRUS": {
        "unidad": 0,
        "almacen": 0,
        "total": 0
      },
      "TDPA": {
        "unidad": 0,
        "almacen": 1144,
        "total": 1144
      },
      "TRIPLE VIRAL (S...)": {
        "unidad": 550,
        "almacen": 13375,
        "total": 13925
      },
      "VACUNA ANTIR...": {
        "unidad": 0,
        "almacen": 2,
        "total": 2
      }
    }
  },
  "Farmacia HGSZ-MF 13": {
    "zona": "NORTE",
    "vacunas": {
      "ANTIVIPERINO": {
        "unidad": 0,
        "almacen": 290,
        "total": 290
      },
      "BCG": {
        "unidad": 0,
        "almacen": 176,
        "total": 176
      },
      "DOBLE VIRAL (SR)": {
        "unidad": 0,
        "almacen": 60,
        "total": 60
      },
      "GAMA ANITETA...": {
        "unidad": 0,
        "almacen": 14,
        "total": 14
      },
      "GAMA ANITRA...": {
        "unidad": 0,
        "almacen": 1,
        "total": 1
      },
      "HEPATITIS A AD...": {
        "unidad": 0,
        "almacen": 64,
        "total": 64
      },
      "HEPATITIS B": {
        "unidad": 0,
        "almacen": 264,
        "total": 264
      },
      "TD": {
        "unidad": 0,
        "almacen": 0,
        "total": 0
      },
      "TDPA": {
        "unidad": 0,
        "almacen": 1144,
        "total": 1144
      },
      "VITAMINA A": {
        "unidad": 0,
        "almacen": 4755,
        "total": 4755
      }
    }
  },
  "Farmacia HGZ 11": {
    "zona": "NORTE",
    "vacunas": {
      "ANTIALACRAN": {
        "unidad": 0,
        "almacen": 252,
        "total": 252
      },
      "ANTIARACNIDO F/I": {
        "unidad": 0,
        "almacen": 341,
        "total": 341
      },
      "ANTIVIPERINO": {
        "unidad": 0,
        "almacen": 290,
        "total": 290
      },
      "BCG": {
        "unidad": 0,
        "almacen": 176,
        "total": 176
      },
      "DOBLE VIRAL (SR)": {
        "unidad": 0,
        "almacen": 60,
        "total": 60
      },
      "GAMA ANITETA...": {
        "unidad": 0,
        "almacen": 14,
        "total": 14
      },
      "GAMA ANITRA...": {
        "unidad": 0,
        "almacen": 1,
        "total": 1
      },
      "HEPATITIS A AD...": {
        "unidad": 0,
        "almacen": 64,
        "total": 64
      },
      "HEPATITIS B": {
        "unidad": 0,
        "almacen": 264,
        "total": 264
      },
      "TD": {
        "unidad": 0,
        "almacen": 0,
        "total": 0
      },
      "TDPA": {
        "unidad": 0,
        "almacen": 1144,
        "total": 1144
      },
      "TRIPLE VIRAL (S...)": {
        "unidad": 4100,
        "almacen": 13375,
        "total": 17475
      },
      "VACUNA ANTIR...": {
        "unidad": 0,
        "almacen": 2,
        "total": 2
      },
      "VITAMINA A": {
        "unidad": 0,
        "almacen": 4755,
        "total": 4755
      }
    }
  },
  "Farmacia UMF 79": {
    "zona": "NORTE",
    "vacunas": {
      "BCG": {
        "unidad": 0,
        "almacen": 176,
        "total": 176
      },
      "COVID-19": {
        "unidad": 0,
        "almacen": 95,
        "total": 95
      },
      "DOBLE VIRAL (SR)": {
        "unidad": 475,
        "almacen": 60,
        "total": 535
      },
      "DPT": {
        "unidad": 0,
        "almacen": 578,
        "total": 578
      },
      "HEPATITIS A": {
        "unidad": 0,
        "almacen": 8,
        "total": 8
      },
      "HEPATITIS A AD...": {
        "unidad": 10,
        "almacen": 64,
        "total": 74
      },
      "HEPATITIS B": {
        "unidad": 51,
        "almacen": 264,
        "total": 315
      },
      "HEXAVALENTE": {
        "unidad": 224,
        "almacen": 217,
        "total": 441
      },
      "INFLUENZA TET...": {
        "unidad": 0,
        "almacen": 0,
        "total": 0
      },
      "NEUMO 13 V": {
        "unidad": 137,
        "almacen": 0,
        "total": 137
      },
      "NEUMO 20 V": {
        "unidad": 0,
        "almacen": 1620,
        "total": 1620
      },
      "ROTAVIRUS": {
        "unidad": 10,
        "almacen": 0,
        "total": 10
      },
      "TD": {
        "unidad": 151,
        "almacen": 0,
        "total": 151
      },
      "TDPA": {
        "unidad": 483,
        "almacen": 1144,
        "total": 1627
      },
      "TRIPLE VIRAL (S...)": {
        "unidad": 1350,
        "almacen": 13375,
        "total": 14725
      },
      "VACUNA ANTIR...": {
        "unidad": 0,
        "almacen": 2,
        "total": 2
      },
      "VHP 9 V": {
        "unidad": 0,
        "almacen": 17,
        "total": 17
      },
      "VITAMINA A": {
        "unidad": 0,
        "almacen": 4755,
        "total": 4755
      }
    }
  },
  "Direccion UMF 3": {
    "zona": "SUR",
    "vacunas": {
      "BCG": {
        "unidad": 0,
        "almacen": 176,
        "total": 176
      },
      "COVID-19": {
        "unidad": 5,
        "almacen": 95,
        "total": 100
      },
      "DOBLE VIRAL (SR)": {
        "unidad": 200,
        "almacen": 60,
        "total": 260
      },
      "DPT": {
        "unidad": 0,
        "almacen": 578,
        "total": 578
      },
      "HEPATITIS A AD...": {
        "unidad": 30,
        "almacen": 64,
        "total": 94
      },
      "HEPATITIS B": {
        "unidad": 20,
        "almacen": 264,
        "total": 284
      },
      "HEXAVALENTE": {
        "unidad": 32,
        "almacen": 217,
        "total": 249
      },
      "INFLUENZA TET...": {
        "unidad": 30,
        "almacen": 0,
        "total": 30
      },
      "NEUMO 13 V": {
        "unidad": 40,
        "almacen": 0,
        "total": 40
      },
      "NEUMO 20 V": {
        "unidad": 0,
        "almacen": 1620,
        "total": 1620
      },
      "ROTAVIRUS": {
        "unidad": 8,
        "almacen": 0,
        "total": 8
      },
      "TDPA": {
        "unidad": 50,
        "almacen": 1144,
        "total": 1194
      },
      "TRIPLE VIRAL (S...)": {
        "unidad": 1200,
        "almacen": 13375,
        "total": 14575
      },
      "VACUNA ANTIR...": {
        "unidad": 2,
        "almacen": 2,
        "total": 4
      },
      "VITAMINA A": {
        "unidad": 40,
        "almacen": 4755,
        "total": 4795
      }
    }
  },
  "Direccion UMF 4": {
    "zona": "SUR",
    "vacunas": {
      "ANTIALACRAN": {
        "unidad": 1,
        "almacen": 252,
        "total": 253
      },
      "ANTIARACNIDO F/I": {
        "unidad": 2,
        "almacen": 341,
        "total": 343
      },
      "BCG": {
        "unidad": 0,
        "almacen": 176,
        "total": 176
      },
      "COVID-19": {
        "unidad": 5,
        "almacen": 95,
        "total": 100
      },
      "DOBLE VIRAL (SR)": {
        "unidad": 76,
        "almacen": 60,
        "total": 136
      },
      "DPT": {
        "unidad": 10,
        "almacen": 578,
        "total": 588
      },
      "HEPATITIS A AD...": {
        "unidad": 10,
        "almacen": 64,
        "total": 74
      },
      "HEPATITIS B": {
        "unidad": 10,
        "almacen": 264,
        "total": 274
      },
      "HEXAVALENTE": {
        "unidad": 6,
        "almacen": 217,
        "total": 223
      },
      "NEUMO 13 V": {
        "unidad": 1,
        "almacen": 0,
        "total": 1
      },
      "NEUMO 20 V": {
        "unidad": 0,
        "almacen": 1620,
        "total": 1620
      },
      "ROTAVIRUS": {
        "unidad": 0,
        "almacen": 0,
        "total": 0
      },
      "TDPA": {
        "unidad": 6,
        "almacen": 1144,
        "total": 1150
      },
      "TRIPLE VIRAL (S...)": {
        "unidad": 206,
        "almacen": 13375,
        "total": 13581
      },
      "VHP 9 V": {
        "unidad": 10,
        "almacen": 17,
        "total": 27
      },
      "VITAMINA A": {
        "unidad": 40,
        "almacen": 4755,
        "total": 4795
      }
    }
  },
  "Direccion UMF 62": {
    "zona": "SUR",
    "vacunas": {
      "ANTIALACRAN": {
        "unidad": 6,
        "almacen": 252,
        "total": 258
      },
      "ANTIARACNIDO F/I": {
        "unidad": 3,
        "almacen": 341,
        "total": 344
      },
      "ANTIVIPERINO": {
        "unidad": 3,
        "almacen": 290,
        "total": 293
      },
      "BCG": {
        "unidad": 0,
        "almacen": 176,
        "total": 176
      },
      "COVID-19": {
        "unidad": 5,
        "almacen": 95,
        "total": 100
      },
      "DOBLE VIRAL (SR)": {
        "unidad": 61,
        "almacen": 60,
        "total": 121
      },
      "DPT": {
        "unidad": 23,
        "almacen": 578,
        "total": 601
      },
      "HEPATITIS A": {
        "unidad": 0,
        "almacen": 8,
        "total": 8
      },
      "HEPATITIS A AD...": {
        "unidad": 12,
        "almacen": 64,
        "total": 76
      },
      "HEPATITIS B": {
        "unidad": 10,
        "almacen": 264,
        "total": 274
      },
      "HEXAVALENTE": {
        "unidad": 27,
        "almacen": 217,
        "total": 244
      },
      "INFLUENZA TET...": {
        "unidad": 9,
        "almacen": 0,
        "total": 9
      },
      "NEUMO 13 V": {
        "unidad": 53,
        "almacen": 0,
        "total": 53
      },
      "NEUMO 20 V": {
        "unidad": 0,
        "almacen": 1620,
        "total": 1620
      },
      "NEUMO 23 V": {
        "unidad": 20,
        "almacen": 0,
        "total": 20
      },
      "ROTAVIRUS": {
        "unidad": 39,
        "almacen": 0,
        "total": 39
      },
      "TD": {
        "unidad": 60,
        "almacen": 0,
        "total": 60
      },
      "TDPA": {
        "unidad": 24,
        "almacen": 1144,
        "total": 1168
      },
      "TRIPLE VIRAL (S...)": {
        "unidad": 580,
        "almacen": 13375,
        "total": 13955
      },
      "VARICELA": {
        "unidad": 20,
        "almacen": 0,
        "total": 20
      },
      "VITAMINA A": {
        "unidad": 164,
        "almacen": 4755,
        "total": 4919
      }
    }
  },
  "Direccion UMF 70": {
    "zona": "SUR",
    "vacunas": {
      "BCG": {
        "unidad": 5,
        "almacen": 176,
        "total": 181
      },
      "DOBLE VIRAL (SR)": {
        "unidad": 30,
        "almacen": 60,
        "total": 90
      },
      "DPT": {
        "unidad": 15,
        "almacen": 578,
        "total": 593
      },
      "HEPATITIS A": {
        "unidad": 2,
        "almacen": 8,
        "total": 10
      },
      "HEPATITIS A AD...": {
        "unidad": 7,
        "almacen": 64,
        "total": 71
      },
      "HEPATITIS B": {
        "unidad": 20,
        "almacen": 264,
        "total": 284
      },
      "HEXAVALENTE": {
        "unidad": 60,
        "almacen": 217,
        "total": 277
      },
      "NEUMO 13 V": {
        "unidad": 10,
        "almacen": 0,
        "total": 10
      },
      "NEUMO 20 V": {
        "unidad": 54,
        "almacen": 1620,
        "total": 1674
      },
      "ROTAVIRUS": {
        "unidad": 15,
        "almacen": 0,
        "total": 15
      },
      "TDPA": {
        "unidad": 15,
        "almacen": 1144,
        "total": 1159
      },
      "TRIPLE VIRAL (S...)": {
        "unidad": 1370,
        "almacen": 13375,
        "total": 14745
      },
      "VACUNA ANTIR...": {
        "unidad": 1,
        "almacen": 2,
        "total": 3
      }
    }
  },
  "Direccion UMF 88": {
    "zona": "SUR",
    "vacunas": {
      "ANTIALACRAN": {
        "unidad": 5,
        "almacen": 252,
        "total": 257
      },
      "ANTIARACNIDO F/I": {
        "unidad": 25,
        "almacen": 341,
        "total": 366
      },
      "ANTIVIPERINO": {
        "unidad": 8,
        "almacen": 290,
        "total": 298
      },
      "BCG": {
        "unidad": 0,
        "almacen": 176,
        "total": 176
      },
      "COVID-19": {
        "unidad": 21,
        "almacen": 95,
        "total": 116
      },
      "DOBLE VIRAL (SR)": {
        "unidad": 37,
        "almacen": 60,
        "total": 97
      },
      "DPT": {
        "unidad": 29,
        "almacen": 578,
        "total": 607
      },
      "GAMA ANITRA...": {
        "unidad": 0,
        "almacen": 1,
        "total": 1
      },
      "HEPATITIS A": {
        "unidad": 0,
        "almacen": 8,
        "total": 8
      },
      "HEPATITIS A AD...": {
        "unidad": 50,
        "almacen": 64,
        "total": 114
      },
      "HEPATITIS B": {
        "unidad": 39,
        "almacen": 264,
        "total": 303
      },
      "HEXAVALENTE": {
        "unidad": 70,
        "almacen": 217,
        "total": 287
      },
      "INFLUENZA TET...": {
        "unidad": 30,
        "almacen": 0,
        "total": 30
      },
      "NEUMO 13 V": {
        "unidad": 10,
        "almacen": 0,
        "total": 10
      },
      "NEUMO 20 V": {
        "unidad": 0,
        "almacen": 1620,
        "total": 1620
      },
      "NEUMO 23 V": {
        "unidad": 0,
        "almacen": 0,
        "total": 0
      },
      "ROTAVIRUS": {
        "unidad": 38,
        "almacen": 0,
        "total": 38
      },
      "TD": {
        "unidad": 0,
        "almacen": 0,
        "total": 0
      },
      "TDPA": {
        "unidad": 107,
        "almacen": 1144,
        "total": 1251
      },
      "TRIPLE VIRAL (S...)": {
        "unidad": 400,
        "almacen": 13375,
        "total": 13775
      },
      "VACUNA ANTIR...": {
        "unidad": 2,
        "almacen": 2,
        "total": 4
      },
      "VARICELA": {
        "unidad": 0,
        "almacen": 0,
        "total": 0
      },
      "VHP 9 V": {
        "unidad": 38,
        "almacen": 17,
        "total": 55
      },
      "VITAMINA A": {
        "unidad": 150,
        "almacen": 4755,
        "total": 4905
      }
    }
  },
  "Farmacia HGZ-MF 2": {
    "zona": "SUR",
    "vacunas": {
      "ANTIALACRAN": {
        "unidad": 0,
        "almacen": 252,
        "total": 252
      },
      "ANTIARACNIDO F/I": {
        "unidad": 0,
        "almacen": 341,
        "total": 341
      },
      "ANTICORALILLO": {
        "unidad": 0,
        "almacen": 1,
        "total": 1
      },
      "ANTIVIPERINO": {
        "unidad": 0,
        "almacen": 290,
        "total": 290
      },
      "BCG": {
        "unidad": 54,
        "almacen": 176,
        "total": 230
      },
      "COVID-19": {
        "unidad": 66,
        "almacen": 95,
        "total": 161
      },
      "DOBLE VIRAL (SR)": {
        "unidad": 1967,
        "almacen": 60,
        "total": 2027
      },
      "DPT": {
        "unidad": 0,
        "almacen": 578,
        "total": 578
      },
      "GAMA ANITETA...": {
        "unidad": 0,
        "almacen": 14,
        "total": 14
      },
      "GAMA ANITRA...": {
        "unidad": 5,
        "almacen": 1,
        "total": 6
      },
      "HEPATITIS A": {
        "unidad": 0,
        "almacen": 8,
        "total": 8
      },
      "HEPATITIS A AD...": {
        "unidad": 80,
        "almacen": 64,
        "total": 144
      },
      "HEPATITIS B": {
        "unidad": 100,
        "almacen": 264,
        "total": 364
      },
      "HEXAVALENTE": {
        "unidad": 0,
        "almacen": 217,
        "total": 217
      },
      "INFLUENZA TET...": {
        "unidad": 0,
        "almacen": 0,
        "total": 0
      },
      "NEUMO 13 V": {
        "unidad": 0,
        "almacen": 0,
        "total": 0
      },
      "NEUMO 20 V": {
        "unidad": 0,
        "almacen": 1620,
        "total": 1620
      },
      "ROTAVIRUS": {
        "unidad": 0,
        "almacen": 0,
        "total": 0
      },
      "TD": {
        "unidad": 0,
        "almacen": 0,
        "total": 0
      },
      "TDPA": {
        "unidad": 0,
        "almacen": 1144,
        "total": 1144
      },
      "TRIPLE VIRAL (S...)": {
        "unidad": 6000,
        "almacen": 13375,
        "total": 19375
      },
      "VACUNA ANTIR...": {
        "unidad": 0,
        "almacen": 2,
        "total": 2
      },
      "VARICELA": {
        "unidad": 159,
        "almacen": 0,
        "total": 159
      },
      "VHP 9 V": {
        "unidad": 103,
        "almacen": 17,
        "total": 120
      },
      "VITAMINA A": {
        "unidad": 105,
        "almacen": 4755,
        "total": 4860
      }
    }
  },
  "Farmacia HRS Ramos": {
    "zona": "SUR",
    "vacunas": {
      "ANTIALACRAN": {
        "unidad": 0,
        "almacen": 252,
        "total": 252
      },
      "ANTIVIPERINO": {
        "unidad": 0,
        "almacen": 290,
        "total": 290
      },
      "BCG": {
        "unidad": 0,
        "almacen": 176,
        "total": 176
      },
      "COVID-19": {
        "unidad": 0,
        "almacen": 95,
        "total": 95
      },
      "DOBLE VIRAL (SR)": {
        "unidad": 0,
        "almacen": 60,
        "total": 60
      },
      "DPT": {
        "unidad": 0,
        "almacen": 578,
        "total": 578
      },
      "HEPATITIS B": {
        "unidad": 0,
        "almacen": 264,
        "total": 264
      },
      "HEXAVALENTE": {
        "unidad": 0,
        "almacen": 217,
        "total": 217
      },
      "INFLUENZA TET...": {
        "unidad": 0,
        "almacen": 0,
        "total": 0
      },
      "NEUMO 13 V": {
        "unidad": 0,
        "almacen": 0,
        "total": 0
      },
      "ROTAVIRUS": {
        "unidad": 0,
        "almacen": 0,
        "total": 0
      },
      "TD": {
        "unidad": 0,
        "almacen": 0,
        "total": 0
      },
      "TDPA": {
        "unidad": 0,
        "almacen": 1144,
        "total": 1144
      },
      "TRIPLE VIRAL (S...)": {
        "unidad": 0,
        "almacen": 13375,
        "total": 13375
      },
      "VACUNA ANTIR...": {
        "unidad": 0,
        "almacen": 2,
        "total": 2
      },
      "VHP 9 V": {
        "unidad": 0,
        "almacen": 17,
        "total": 17
      }
    }
  },
  "Farmacia UMAA 89": {
    "zona": "SUR",
    "vacunas": {
      "ANTIARACNIDO F/I": {
        "unidad": 0,
        "almacen": 341,
        "total": 341
      },
      "ANTIVIPERINO": {
        "unidad": 0,
        "almacen": 290,
        "total": 290
      },
      "BCG": {
        "unidad": 4,
        "almacen": 176,
        "total": 180
      },
      "COVID-19": {
        "unidad": 0,
        "almacen": 95,
        "total": 95
      },
      "DOBLE VIRAL (SR)": {
        "unidad": 165,
        "almacen": 60,
        "total": 225
      },
      "DPT": {
        "unidad": 0,
        "almacen": 578,
        "total": 578
      },
      "GAMA ANITETA...": {
        "unidad": 0,
        "almacen": 14,
        "total": 14
      },
      "GAMA ANITRA...": {
        "unidad": 0,
        "almacen": 1,
        "total": 1
      },
      "HEPATITIS A": {
        "unidad": 0,
        "almacen": 8,
        "total": 8
      },
      "HEPATITIS A AD...": {
        "unidad": 50,
        "almacen": 64,
        "total": 114
      },
      "HEPATITIS B": {
        "unidad": 2,
        "almacen": 264,
        "total": 266
      },
      "HEXAVALENTE": {
        "unidad": 22,
        "almacen": 217,
        "total": 239
      },
      "INFLUENZA TET...": {
        "unidad": 0,
        "almacen": 0,
        "total": 0
      },
      "NEUMO 13 V": {
        "unidad": 0,
        "almacen": 0,
        "total": 0
      },
      "NEUMO 20 V": {
        "unidad": 0,
        "almacen": 1620,
        "total": 1620
      },
      "NEUMO 23 V": {
        "unidad": 0,
        "almacen": 0,
        "total": 0
      },
      "ROTAVIRUS": {
        "unidad": 11,
        "almacen": 0,
        "total": 11
      },
      "TD": {
        "unidad": 93,
        "almacen": 0,
        "total": 93
      },
      "TDPA": {
        "unidad": 168,
        "almacen": 1144,
        "total": 1312
      },
      "TRIPLE VIRAL (S...)": {
        "unidad": 200,
        "almacen": 13375,
        "total": 13575
      },
      "VACUNA ANTIR...": {
        "unidad": 0,
        "almacen": 2,
        "total": 2
      },
      "VHP 9 V": {
        "unidad": 107,
        "almacen": 17,
        "total": 124
      },
      "VITAMINA A": {
        "unidad": 0,
        "almacen": 4755,
        "total": 4755
      }
    }
  },
  "Farmacia UMF 73": {
    "zona": "SUR",
    "vacunas": {
      "ANTIALACRAN": {
        "unidad": 51,
        "almacen": 252,
        "total": 303
      },
      "ANTIARACNIDO F/I": {
        "unidad": 70,
        "almacen": 341,
        "total": 411
      },
      "ANTICORALILLO": {
        "unidad": 5,
        "almacen": 1,
        "total": 6
      },
      "ANTIVIPERINO": {
        "unidad": 50,
        "almacen": 290,
        "total": 340
      },
      "BCG": {
        "unidad": 0,
        "almacen": 176,
        "total": 176
      },
      "COVID-19": {
        "unidad": 0,
        "almacen": 95,
        "total": 95
      },
      "DOBLE VIRAL (SR)": {
        "unidad": 0,
        "almacen": 60,
        "total": 60
      },
      "DPT": {
        "unidad": 204,
        "almacen": 578,
        "total": 782
      },
      "GAMA ANITETA...": {
        "unidad": 14,
        "almacen": 14,
        "total": 28
      },
      "GAMA ANITRA...": {
        "unidad": 5,
        "almacen": 1,
        "total": 6
      },
      "HEPATITIS A": {
        "unidad": 120,
        "almacen": 8,
        "total": 128
      },
      "HEPATITIS A AD...": {
        "unidad": 0,
        "almacen": 64,
        "total": 64
      },
      "HEPATITIS B": {
        "unidad": 0,
        "almacen": 264,
        "total": 264
      },
      "HEXAVALENTE": {
        "unidad": 202,
        "almacen": 217,
        "total": 419
      },
      "INFLUENZA TET...": {
        "unidad": 0,
        "almacen": 0,
        "total": 0
      },
      "NEUMO 13 V": {
        "unidad": 0,
        "almacen": 0,
        "total": 0
      },
      "NEUMO 20 V": {
        "unidad": 0,
        "almacen": 1620,
        "total": 1620
      },
      "NEUMO 23 V": {
        "unidad": 0,
        "almacen": 0,
        "total": 0
      },
      "ROTAVIRUS": {
        "unidad": 0,
        "almacen": 0,
        "total": 0
      },
      "TD": {
        "unidad": 397,
        "almacen": 0,
        "total": 397
      },
      "TDPA": {
        "unidad": 1881,
        "almacen": 1144,
        "total": 3025
      },
      "TRIPLE VIRAL (S...)": {
        "unidad": 0,
        "almacen": 13375,
        "total": 13375
      },
      "VACUNA ANTIR...": {
        "unidad": 0,
        "almacen": 2,
        "total": 2
      },
      "VARICELA": {
        "unidad": 0,
        "almacen": 0,
        "total": 0
      },
      "VHP 9 V": {
        "unidad": 75,
        "almacen": 17,
        "total": 92
      },
      "VITAMINA A": {
        "unidad": 0,
        "almacen": 4755,
        "total": 4755
      }
    }
  },
  "Farmacia UMF 82": {
    "zona": "SUR",
    "vacunas": {
      "ANTIALACRAN": {
        "unidad": 3,
        "almacen": 252,
        "total": 255
      },
      "ANTIARACNIDO F/I": {
        "unidad": 20,
        "almacen": 341,
        "total": 361
      },
      "ANTIVIPERINO": {
        "unidad": 10,
        "almacen": 290,
        "total": 300
      },
      "BCG": {
        "unidad": 45,
        "almacen": 176,
        "total": 221
      },
      "COVID-19": {
        "unidad": 47,
        "almacen": 95,
        "total": 142
      },
      "DOBLE VIRAL (SR)": {
        "unidad": 0,
        "almacen": 60,
        "total": 60
      },
      "DPT": {
        "unidad": 54,
        "almacen": 578,
        "total": 632
      },
      "GAMA ANITETA...": {
        "unidad": 0,
        "almacen": 14,
        "total": 14
      },
      "GAMA ANITRA...": {
        "unidad": 14,
        "almacen": 1,
        "total": 15
      },
      "HEPATITIS A": {
        "unidad": 0,
        "almacen": 8,
        "total": 8
      },
      "HEPATITIS A AD...": {
        "unidad": 10,
        "almacen": 64,
        "total": 74
      },
      "HEPATITIS B": {
        "unidad": 66,
        "almacen": 264,
        "total": 330
      },
      "HEXAVALENTE": {
        "unidad": 11,
        "almacen": 217,
        "total": 228
      },
      "INFLUENZA TET...": {
        "unidad": 64,
        "almacen": 0,
        "total": 64
      },
      "NEUMO 13 V": {
        "unidad": 14,
        "almacen": 0,
        "total": 14
      },
      "NEUMO 20 V": {
        "unidad": 0,
        "almacen": 1620,
        "total": 1620
      },
      "NEUMO 23 V": {
        "unidad": 0,
        "almacen": 0,
        "total": 0
      },
      "ROTAVIRUS": {
        "unidad": 30,
        "almacen": 0,
        "total": 30
      },
      "TD": {
        "unidad": 220,
        "almacen": 0,
        "total": 220
      },
      "TDPA": {
        "unidad": 1507,
        "almacen": 1144,
        "total": 2651
      },
      "TRIPLE VIRAL (S...)": {
        "unidad": 0,
        "almacen": 13375,
        "total": 13375
      },
      "VACUNA ANTIR...": {
        "unidad": 10,
        "almacen": 2,
        "total": 12
      },
      "VARICELA": {
        "unidad": 0,
        "almacen": 0,
        "total": 0
      },
      "VHP 9 V": {
        "unidad": 72,
        "almacen": 17,
        "total": 89
      },
      "VITAMINA A": {
        "unidad": 0,
        "almacen": 4755,
        "total": 4755
      }
    }
  },
  "Farmacia UMF 91": {
    "zona": "SUR",
    "vacunas": {
      "ANTIALACRAN": {
        "unidad": 3,
        "almacen": 252,
        "total": 255
      },
      "ANTIARACNIDO F/I": {
        "unidad": 0,
        "almacen": 341,
        "total": 341
      },
      "ANTIVIPERINO": {
        "unidad": 12,
        "almacen": 290,
        "total": 302
      },
      "BCG": {
        "unidad": 20,
        "almacen": 176,
        "total": 196
      },
      "COVID-19": {
        "unidad": 0,
        "almacen": 95,
        "total": 95
      },
      "DOBLE VIRAL (SR)": {
        "unidad": 50,
        "almacen": 60,
        "total": 110
      },
      "DPT": {
        "unidad": 0,
        "almacen": 578,
        "total": 578
      },
      "GAMA ANITETA...": {
        "unidad": 0,
        "almacen": 14,
        "total": 14
      },
      "GAMA ANITRA...": {
        "unidad": 0,
        "almacen": 1,
        "total": 1
      },
      "HEPATITIS A": {
        "unidad": 40,
        "almacen": 8,
        "total": 48
      },
      "HEPATITIS B": {
        "unidad": 40,
        "almacen": 264,
        "total": 304
      },
      "HEXAVALENTE": {
        "unidad": 126,
        "almacen": 217,
        "total": 343
      },
      "INFLUENZA TET...": {
        "unidad": 0,
        "almacen": 0,
        "total": 0
      },
      "NEUMO 13 V": {
        "unidad": 0,
        "almacen": 0,
        "total": 0
      },
      "NEUMO 23 V": {
        "unidad": 0,
        "almacen": 0,
        "total": 0
      },
      "ROTAVIRUS": {
        "unidad": 11,
        "almacen": 0,
        "total": 11
      },
      "TD": {
        "unidad": 10,
        "almacen": 0,
        "total": 10
      },
      "TDPA": {
        "unidad": 0,
        "almacen": 1144,
        "total": 1144
      },
      "TRIPLE VIRAL (S...)": {
        "unidad": 400,
        "almacen": 13375,
        "total": 13775
      },
      "VACUNA ANTIR...": {
        "unidad": 0,
        "almacen": 2,
        "total": 2
      },
      "VARICELA": {
        "unidad": 0,
        "almacen": 0,
        "total": 0
      },
      "VHP 9 V": {
        "unidad": 0,
        "almacen": 17,
        "total": 17
      },
      "VITAMINA A": {
        "unidad": 0,
        "almacen": 4755,
        "total": 4755
      }
    }
  }
}